dependencyhider/__init__.py
dependencyhider-0.1.3.dist-info/METADATA
dependencyhider-0.1.3.dist-info/WHEEL
dependencyhider-0.1.3.dist-info/top_level.txt
dependencyhider-0.1.3.dist-info/RECORD
