Metadata-Version: 2.1
Name: dependencyhider
Version: 0.1.3
Summary: This is a package created purely for research purposes. It intends to download a package that is not in the setup.py file. 
Home-page: UNKNOWN
Author: Farida Shafik
Author-email: faridashafik@gmail.com
License: Dont use this
Platform: UNKNOWN
Classifier: Development Status :: 1 - Planning
Classifier: Intended Audience :: Science/Research
Classifier: License :: OSI Approved :: BSD License
Classifier: Operating System :: POSIX :: Linux
Classifier: Programming Language :: Python :: 2
Classifier: Programming Language :: Python :: 2.7
Classifier: Programming Language :: Python :: 3
Classifier: Programming Language :: Python :: 3.4
Classifier: Programming Language :: Python :: 3.5
Requires-Dist: numpy
